searchagent/__init__.py
searchagent/prompts.json
searchagent/prompts.py
searchagent-0.0.2.dist-info/METADATA
searchagent-0.0.2.dist-info/WHEEL
searchagent-0.0.2.dist-info/licenses/LICENSE.txt
searchagent-0.0.2.dist-info/RECORD
